{
  "platform_id": "twitter",
  "page_type_id": "timeline",
  "page_type_id": "timeline",
  "display_name": "Home Timeline",
  "url_patterns": [
    "/home",
    "/"
  ],
  "root_selector": "main",
  "content_schemas": [
    {
      "content_type": "tweet",
      "semantic_role": "article",
      "container_selector": {
        "primary": {
          "type": "css",
          "value": "article[data-testid='tweet']"
        },
        "fallbacks": [],
        "scope": "container"
      },
      "is_list": true,
      "fields": [
        {
          "name": "author_name",
          "field_type": "text",
          "selector": {
            "primary": {
              "type": "css",
              "value": "[data-testid='User-Name'] span:first-child"
            },
            "fallbacks": [],
            "scope": "container"
          },
          "extraction": "text",
          "required": false,
          "transform": "trim"
        },
        {
          "name": "author_handle",
          "field_type": "text",
          "selector": {
            "primary": {
              "type": "css",
              "value": "[data-testid='User-Name'] a[href^='/']"
            },
            "fallbacks": [],
            "scope": "container"
          },
          "extraction": {
            "attribute": "href"
          },
          "pattern": "/[\\w]+",
          "required": false,
          "transform": "trim"
        },
        {
          "name": "content",
          "field_type": "text",
          "selector": {
            "primary": {
              "type": "css",
              "value": "[data-testid='tweetText']"
            },
            "fallbacks": [],
            "scope": "container"
          },
          "extraction": "text",
          "required": false,
          "transform": "trim"
        }
      ],
      "actions": [],
      "nested_content": [],
      "required_fields": []
    }
  ],
  "page_actions": [
    {
      "action_type": "input",
      "semantic_intent": "compose",
      "selector": {
        "primary": {
          "type": "css",
          "value": "[data-testid='tweetTextarea_0']"
        },
        "fallbacks": [],
        "scope": "container"
      },
      "requires_input": {
        "input_selector": {
          "primary": {
            "type": "css",
            "value": "[data-testid='tweetTextarea_0']"
          },
          "fallbacks": [],
          "scope": "container"
        },
        "input_type": "rich_text",
        "placeholder": "What is happening?!"
      },
      "requires_confirmation": true,
      "risk_level": 6
    }
  ],
  "domains": [
    "twitter.com",
    "x.com",
    "www.twitter.com",
    "www.x.com"
  ],
  "cid": "bafk2687f24486862d874acc19d3a2686ab7cc0d4a51",
  "version": "1.0.0"
}